{"type":"photo","flickr_type":"photo","title":"StriimiPiiri-at-Telegram","author_name":"Jarmo #Striimivaari Lahti","author_url":"https:\/\/www.flickr.com\/photos\/jarmolahti\/","width":996,"height":930,"url":"https:\/\/live.staticflickr.com\/65535\/50898954251_556c238a59_b.jpg","web_page":"https:\/\/www.flickr.com\/photos\/jarmolahti\/50898954251\/","thumbnail_url":"https:\/\/live.staticflickr.com\/65535\/50898954251_556c238a59_q.jpg","thumbnail_width":150,"thumbnail_height":150,"web_page_short_url":"https:\/\/flic.kr\/p\/2kxLrNK","license":"All Rights Reserved","license_id":0,"html":"<a data-flickr-embed=\"true\" href=\"https:\/\/www.flickr.com\/photos\/jarmolahti\/50898954251\/\" title=\"StriimiPiiri-at-Telegram by Jarmo #Striimivaari Lahti, on Flickr\"><img src=\"https:\/\/live.staticflickr.com\/65535\/50898954251_556c238a59_b.jpg\" width=\"996\" height=\"930\" alt=\"StriimiPiiri-at-Telegram\"><\/a><script async src=\"https:\/\/embedr.flickr.com\/assets\/client-code.js\" charset=\"utf-8\"><\/script>","version":"1.0","cache_age":3600,"provider_name":"Flickr","provider_url":"https:\/\/www.flickr.com\/"}
